imgvisfeat/AbstractVisualizer.py
imgvisfeat/ColorChannelVisualizer.py
imgvisfeat/GradientVisualizer.py
imgvisfeat/HoGVisualizer.py
imgvisfeat/KeypointVisualizer.py
imgvisfeat/LBPVisualizer.py
imgvisfeat/PowerSpectrumVisualizer.py
imgvisfeat/Visualizer.py
imgvisfeat/__init__.py
imgvisfeat/cli.py
imgvisfeat/type.py
imgvisfeat-0.0.5.dist-info/WHEEL
imgvisfeat-0.0.5.dist-info/entry_points.txt
imgvisfeat-0.0.5.dist-info/METADATA
imgvisfeat-0.0.5.dist-info/RECORD
