Metadata-Version: 2.3
Name: ImgVisFeat
Version: 0.0.5
Summary: Image Visualization and Feature Extraction Library
Keywords: image_processing,feature_extraction,visualization
Author: chatflip
Author-email: chatflip <oo.chat.flip@gmail.com>
License: MIT
Classifier: Development Status :: 1 - Planning
Classifier: Intended Audience :: Developers
Classifier: Intended Audience :: Education
Classifier: License :: OSI Approved :: MIT License
Classifier: Programming Language :: Python :: 3
Classifier: Programming Language :: Python :: 3.10
Classifier: Programming Language :: Python :: 3.11
Classifier: Programming Language :: Python :: 3.12
Classifier: Programming Language :: Python :: 3.13
Classifier: Programming Language :: Python :: 3.14
Classifier: Topic :: Software Development :: Libraries :: Python Modules
Classifier: Topic :: Education
Classifier: Topic :: Scientific/Engineering :: Image Recognition
Requires-Dist: numpy
Requires-Dist: opencv-python
Requires-Dist: pydantic>=2.0.0
Requires-Dist: scikit-image
Requires-Python: >=3.10, <4.0
Project-URL: Documentation, https://chatflip.github.io/ImgVisFeat
Project-URL: Homepage, https://github.com/chatflip/ImgVisFeat
Project-URL: Issues, https://github.com/chatflip/ImgVisFeat/issues
Project-URL: Repository, https://github.com/chatflip/ImgVisFeat
